MANIFEST.in
README.md
setup.py
django_webnodes.egg-info/PKG-INFO
django_webnodes.egg-info/SOURCES.txt
django_webnodes.egg-info/dependency_links.txt
django_webnodes.egg-info/not-zip-safe
django_webnodes.egg-info/requires.txt
django_webnodes.egg-info/top_level.txt
webnodes/__init__.py
webnodes/base.py
webnodes/loading.py
webnodes/ext/__init__.py
webnodes/ext/urls.py
webnodes/ext/views.py
webnodes/templatetags/__init__.py
webnodes/templatetags/webnode.py