Metadata-Version: 1.0
Name: django-webnodes
Version: 0.0.3
Summary: Re-usable bussiness components, modular units on a page
Home-page: https://github.com/iamsk/django-webnodes
Author: iamsk
Author-email: iamsk.info@gmail.com
License: UNKNOWN
Platform: UNKNOWN
Classifier: Development Status :: 3 - Alpha
Classifier: Environment :: Web Environment
Classifier: Framework :: Django
Classifier: Intended Audience :: Developers
Classifier: License :: OSI Approved :: MIT License
Classifier: Operating System :: OS Independent
Classifier: Programming Language :: Python
Classifier: Programming Language :: Python :: 2.6
Classifier: Programming Language :: Python :: 2.7
